tableau_utilities/__init__.py
tableau_utilities/fetch_all_cols.py
tableau_utilities/scripted_testing.py
tableau_utilities/test_tableau_utilities.py
tableau_utilities/general/__init__.py
tableau_utilities/general/cli_styling.py
tableau_utilities/general/config_column_persona.py
tableau_utilities/general/funcs.py
tableau_utilities/hyper/__init__.py
tableau_utilities/hyper/hyper.py
tableau_utilities/scripts/__init__.py
tableau_utilities/scripts/apply_configs.py
tableau_utilities/scripts/cli.py
tableau_utilities/scripts/csv_config.py
tableau_utilities/scripts/datasource.py
tableau_utilities/scripts/gen_config.py
tableau_utilities/scripts/merge_config.py
tableau_utilities/scripts/server_info.py
tableau_utilities/scripts/server_operate.py
tableau_utilities/tableau_file/__init__.py
tableau_utilities/tableau_file/tableau_file.py
tableau_utilities/tableau_file/tableau_file_objects.py
tableau_utilities/tableau_server/__init__.py
tableau_utilities/tableau_server/base.py
tableau_utilities/tableau_server/create.py
tableau_utilities/tableau_server/download.py
tableau_utilities/tableau_server/get.py
tableau_utilities/tableau_server/publish.py
tableau_utilities/tableau_server/refresh.py
tableau_utilities/tableau_server/static.py
tableau_utilities/tableau_server/tableau_server.py
tableau_utilities/tableau_server/tableau_server_objects.py
tableau_utilities/tableau_server/update.py
tableau_utilities-2.2.15.dist-info/LICENSE
tableau_utilities-2.2.15.dist-info/METADATA
tableau_utilities-2.2.15.dist-info/WHEEL
tableau_utilities-2.2.15.dist-info/entry_points.txt
tableau_utilities-2.2.15.dist-info/top_level.txt
tableau_utilities-2.2.15.dist-info/RECORD
