Metadata-Version: 2.2
Name: tableau_utilities
Version: 2.2.15
Summary: Utility for maintaining Tableau objects
Home-page: http://pypi.python.org/pypi/tableau-utilities/
Author: Justin Grilli
Author-email: justin.grilli@gmail.com
License: MIT
License-File: LICENSE
Requires-Dist: xmltodict<1.0.0,>=0.12.0
Requires-Dist: pyyaml<7.0.0,>=6.0
Requires-Dist: requests<3.0.0,>=2.27.1
Requires-Dist: pandas<3.0.0,>=2.0.0
Requires-Dist: tabulate<1.0.0,>=0.8.9
Provides-Extra: hyper
Requires-Dist: tableauhyperapi<1.0.0; extra == "hyper"
Dynamic: author
Dynamic: author-email
Dynamic: description
Dynamic: description-content-type
Dynamic: home-page
Dynamic: license
Dynamic: provides-extra
Dynamic: requires-dist
Dynamic: summary
